govtech_data/__init__.py
govtech_data/client.py
govtech_data/models/__init__.py
govtech_data/models/api.py
govtech_data/models/gptactions.py
govtech_data/models/resources/__init__.py
govtech_data/models/resources/datastore_search.py
govtech_data/models/resources/package_list.py
govtech_data/models/resources/package_show.py
govtech_data/models/resources/resource_show.py
govtech_data/prompts/__init__.py
govtech_data/prompts/task.py
govtech_data/utils/__init__.py
govtech_data/utils/commands.py
govtech_data/utils/content.py
govtech_data/utils/openai.py
govtech_data-0.1.23.dist-info/METADATA
govtech_data-0.1.23.dist-info/WHEEL
govtech_data-0.1.23.dist-info/entry_points.txt
govtech_data-0.1.23.dist-info/RECORD
