Metadata-Version: 2.1
Name: govtech-data
Version: 0.1.23
Summary: Library to easily access and read data from data.gov.sg
Home-page: https://github.com/merlin83/govtech-data
License: Singapore Open Data License
Author: Khee-Chin Chua
Author-email: kheechin@gmail.com
Requires-Python: >=3.10,<4.0
Classifier: License :: Other/Proprietary License
Classifier: Programming Language :: Python :: 3
Classifier: Programming Language :: Python :: 3.10
Classifier: Programming Language :: Python :: 3.11
Provides-Extra: openai
Requires-Dist: jsonref (>=1.1.0,<2.0.0)
Requires-Dist: loguru (>=0.7.0,<0.8.0)
Requires-Dist: openai (>=0.27.4,<0.28.0) ; extra == "openai"
Requires-Dist: polars (==0.18.3)
Requires-Dist: pyarrow (>=12.0.0,<13.0.0)
Requires-Dist: pydantic (>=1.10.7,<2.0.0)
Requires-Dist: python-dotenv (>=1.0.0,<2.0.0) ; extra == "openai"
Requires-Dist: python-levenshtein (>=0.21,<0.22)
Requires-Dist: requests (>=2.28.2,<3.0.0)
Requires-Dist: seaborn (>=0.12.2,<0.13.0) ; extra == "openai"
Requires-Dist: thefuzz (>=0.19.0,<0.20.0)
Requires-Dist: tiktoken (==0.4.0) ; extra == "openai"
Project-URL: Repository, https://github.com/merlin83/govtech-data
